grapes_tokenizer/__init__.py
grapes_tokenizer/core.py
grapes_tokenizer-0.1.3.dist-info/licenses/LICENSE
grapes_tokenizer-0.1.3.dist-info/METADATA
grapes_tokenizer-0.1.3.dist-info/WHEEL
grapes_tokenizer-0.1.3.dist-info/top_level.txt
grapes_tokenizer-0.1.3.dist-info/RECORD
